process_data_6/__init__.py
process_data_6/setup.py
process_data_6-0.2.dist-info/METADATA
process_data_6-0.2.dist-info/WHEEL
process_data_6-0.2.dist-info/top_level.txt
process_data_6-0.2.dist-info/RECORD
